edalogparser/__init__.py
edalogparser/base.py
edalogparser/main.py
edalogparser/verible.py
edalogparser/verilator.py
edalogparser/version.py
edalogparser/vivado.py
edalogparser-0.0.2.dist-info/LICENSE
edalogparser-0.0.2.dist-info/METADATA
edalogparser-0.0.2.dist-info/WHEEL
edalogparser-0.0.2.dist-info/entry_points.txt
edalogparser-0.0.2.dist-info/top_level.txt
edalogparser-0.0.2.dist-info/RECORD
