Metadata-Version: 2.1
Name: edalogparser
Version: 0.0.2
Summary: Parse EDA tool output
Home-page: https://github.com/librecores/eda-log-parser
Author: Stefan Wallentowitz
Author-email: stefan@fossi-foundation.org
License: UNKNOWN
Platform: UNKNOWN
Classifier: Development Status :: 3 - Alpha
Classifier: License :: OSI Approved :: MIT License
Classifier: Programming Language :: Python :: 3
